<?xml version="1.0" encoding="utf-8" ?>
<dwsync>
<file name="entremontes-1-media.jpg" server="ftp.elmanco.es/Web/" local="130260655700000000" remote="130875914400000000" Dst="2" />
<file name="articles_clip_image012.jpg" server="ftp.elmanco.es//Web/" local="132432610555956893" remote="130326516000000000" Dst="2" />
<file name="articles_clip_image021.jpg" server="ftp.elmanco.es//Web/" local="132432610560869991" remote="130326516000000000" Dst="2" />
<file name="Atilano Quintero “Tomás”.jpg" server="ftp.elmanco.es//Web/" local="132432610561674311" remote="130326516000000000" Dst="2" />
<file name="caseta-cuesta.jpg" server="ftp.elmanco.es//Web/" local="132432610569584269" remote="130326516000000000" Dst="2" />
<file name="entremontes-1-media.jpg" server="ftp.elmanco.es//Web/" local="132432610572889166" remote="130875192000000000" Dst="2" />
<file name="felix.jpg" server="ftp.elmanco.es//Web/" local="132432610576392854" remote="130326516000000000" Dst="2" />
<file name="Fulgencio Giménez “Salvador”.jpg" server="ftp.elmanco.es//Web/" local="132432610581588834" remote="130326516000000000" Dst="2" />
<file name="image008.jpg" server="ftp.elmanco.es//Web/" local="132432610588810093" remote="130326516000000000" Dst="2" />
<file name="image010.jpg" server="ftp.elmanco.es//Web/" local="132432610589632915" remote="130326516000000000" Dst="2" />
<file name="francisco-pardo.jpg" server="ftp.elmanco.es//Web/" local="132432610592395148" remote="130326516000000000" Dst="2" />
<file name="image012.jpg" server="ftp.elmanco.es//Web/" local="132432610595222544" remote="130326516000000000" Dst="2" />
<file name="image016.jpg" server="ftp.elmanco.es//Web/" local="132432610596114369" remote="130326516000000000" Dst="2" />
<file name="image018.jpg" server="ftp.elmanco.es//Web/" local="132432610598908957" remote="130326516000000000" Dst="2" />
<file name="image023.jpg" server="ftp.elmanco.es//Web/" local="132432610603336430" remote="130326516000000000" Dst="2" />
<file name="image025.jpg" server="ftp.elmanco.es//Web/" local="132432610604916065" remote="130326516000000000" Dst="2" />
<file name="image020.jpg" server="ftp.elmanco.es//Web/" local="132432610607633568" remote="130326516000000000" Dst="2" />
<file name="image030.jpg" server="ftp.elmanco.es//Web/" local="132432610611899100" remote="130326516000000000" Dst="2" />
<file name="image027.jpg" server="ftp.elmanco.es//Web/" local="132432610612808954" remote="130326516000000000" Dst="2" />
<file name="image033.jpg" server="ftp.elmanco.es//Web/" local="132432610613684907" remote="130326516000000000" Dst="2" />
<file name="image035.jpg" server="ftp.elmanco.es//Web/" local="132432610617403241" remote="130326516000000000" Dst="2" />
<file name="image042.jpg" server="ftp.elmanco.es//Web/" local="132432610618143942" remote="130326516000000000" Dst="2" />
<file name="image039.jpg" server="ftp.elmanco.es//Web/" local="132432610618958739" remote="130326516000000000" Dst="2" />
<file name="image045.jpg" server="ftp.elmanco.es//Web/" local="132432610623368737" remote="130326516000000000" Dst="2" />
<file name="image048.jpg" server="ftp.elmanco.es//Web/" local="132432610624115063" remote="130326516000000000" Dst="2" />
<file name="image054.jpg" server="ftp.elmanco.es//Web/" local="132432610626364105" remote="130326516000000000" Dst="2" />
<file name="image061.jpg" server="ftp.elmanco.es//Web/" local="132432610630072583" remote="130326516000000000" Dst="2" />
<file name="image058.jpg" server="ftp.elmanco.es//Web/" local="132432610633386846" remote="130326516000000000" Dst="2" />
<file name="image45.jpg" server="ftp.elmanco.es//Web/" local="132432610635385362" remote="130326516000000000" Dst="2" />
<file name="Jalisco.jpg" server="ftp.elmanco.es//Web/" local="132432610637240531" remote="130326516000000000" Dst="2" />
<file name="Juan_Valiente.jpg" server="ftp.elmanco.es//Web/" local="132432610638409679" remote="130326516000000000" Dst="2" />
</dwsync>