<?xml version="1.0" encoding="utf-8" ?>
<dwsync>
<file name="entrem-5.2-00-cerro moreno.jpg" server="ftp.elmanco.es//Web/" local="132432611013936001" remote="130326516000000000" Dst="2" />
<file name="entrem-5.2-01-andre.jpg" server="ftp.elmanco.es//Web/" local="132432611016720367" remote="130326516000000000" Dst="2" />
<file name="entrem-5.2-02-ramiro.jpg" server="ftp.elmanco.es//Web/" local="132432611019920527" remote="130326516000000000" Dst="2" />
<file name="entrem-5.2-03-jmaria.jpg" server="ftp.elmanco.es//Web/" local="132432611020677326" remote="130326516000000000" Dst="2" />
<file name="entrem-5.2-04-angel.jpg" server="ftp.elmanco.es//Web/" local="132432611021757574" remote="130326516000000000" Dst="2" />
<file name="entrem-5.2-05-candido.jpg" server="ftp.elmanco.es//Web/" local="132432611025484551" remote="130326516000000000" Dst="2" />
<file name="entrem-5.2-06-alfaro.jpg" server="ftp.elmanco.es//Web/" local="132432611026209457" remote="130326516000000000" Dst="2" />
<file name="entrem-5.2-07-manglana.jpg" server="ftp.elmanco.es//Web/" local="132432611027533384" remote="130326516000000000" Dst="2" />
<file name="entrem-5.2-09-smartin.jpg" server="ftp.elmanco.es//Web/" local="132432611031848164" remote="130326516000000000" Dst="2" />
<file name="entrem-5.2-08-ibanez.jpg" server="ftp.elmanco.es//Web/" local="132432611032596176" remote="130326516000000000" Dst="2" />
<file name="entrem-5.2-10-1.jpg" server="ftp.elmanco.es//Web/" local="132432611033857443" remote="130326516000000000" Dst="2" />
<file name="entrem-5.2-10-2.jpg" server="ftp.elmanco.es//Web/" local="132432611036847284" remote="130326516000000000" Dst="2" />
<file name="entrem-5.2-10.jpg" server="ftp.elmanco.es//Web/" local="132432611039189733" remote="130326516000000000" Dst="2" />
<file name="entrem-5.2-11.jpg" server="ftp.elmanco.es//Web/" local="132432611039898143" remote="130326516000000000" Dst="2" />
<file name=".picasa.ini" server="ftp.elmanco.es//Web/" local="132432611041782920" remote="130326516000000000" Dst="2" />
</dwsync>